setup.py
server/__init__.py
server/server_app.py
server/common/__init__.py
server/common/decos.py
server/common/descriptors.py
server/common/errors.py
server/common/metaclasses.py
server/common/settings.py
server/common/utils.py
server/log/__init__.py
server/log/configs/__init__.py
server/log/configs/server_log_config.py
server/server/__init__.py
server/server/server_database.py
server/server/server_gui.py
server/tests/__init__.py
server/tests/test_client.py
server/tests/test_server.py
server/tests/test_utils.py
server_app.egg-info/PKG-INFO
server_app.egg-info/SOURCES.txt
server_app.egg-info/dependency_links.txt
server_app.egg-info/requires.txt
server_app.egg-info/top_level.txt